tap_dbt_artifacts/__init__.py
tap_dbt_artifacts/client.py
tap_dbt_artifacts/schemas/catalog.schema.json
tap_dbt_artifacts/schemas/manifest.schema.json
tap_dbt_artifacts/schemas/run-results.schema.json
tap_dbt_artifacts/schemas/sources.schema.json
tap_dbt_artifacts/streams.py
tap_dbt_artifacts/tap.py
tap_dbt_artifacts/tests/__init__.py
tap_dbt_artifacts/tests/profiles.yml
tap_dbt_artifacts/tests/test_core.py
tap_dbt_artifacts-0.0.5.dist-info/entry_points.txt
tap_dbt_artifacts-0.0.5.dist-info/LICENSE.md
tap_dbt_artifacts-0.0.5.dist-info/WHEEL
tap_dbt_artifacts-0.0.5.dist-info/METADATA
tap_dbt_artifacts-0.0.5.dist-info/RECORD
